pyani_plus/__init__.py
pyani_plus/classify.py
pyani_plus/db_orm.py
pyani_plus/plot_run.py
pyani_plus/private_cli.py
pyani_plus/public_cli.py
pyani_plus/public_cli_args.py
pyani_plus/tools.py
pyani_plus/utils.py
pyani_plus/methods/__init__.py
pyani_plus/methods/anib.py
pyani_plus/methods/anim.py
pyani_plus/methods/dnadiff.py
pyani_plus/methods/external_alignment.py
pyani_plus/methods/fastani.py
pyani_plus/methods/sourmash.py
pyani_plus/workflows/__init__.py
pyani_plus/workflows/compute_column.smk
pyani_plus-1.0.0.dist-info/licenses/LICENSE
pyani_plus-1.0.0.dist-info/METADATA
pyani_plus-1.0.0.dist-info/WHEEL
pyani_plus-1.0.0.dist-info/entry_points.txt
pyani_plus-1.0.0.dist-info/top_level.txt
pyani_plus-1.0.0.dist-info/RECORD
