Metadata-Version: 2.4
Name: pyani-plus
Version: 1.0.0
Summary: pyANI-plus is an application and Python module for whole-genome classification of microbes using Average Nucleotide Identity and similar methods.
Author-email: Leighton Pritchard <leighton.pritchard@strath.ac.uk>, Angelika Kiepas <angelika.kiepas@strath.ac.uk>, "Peter J. A. Cock" <peter.cock@strath.ac.uk>
License-Expression: MIT
Project-URL: homepage, https://github.com/pyani-plus/pyani-plus
Project-URL: source, https://github.com/pyani-plus/pyani-plus
Project-URL: issues, https://github.com/pyani-plus/pyani-plus/issues
Project-URL: documentation, https://pyani-plus.github.io/pyani-plus-docs/
Classifier: Programming Language :: Python :: 3
Classifier: Operating System :: OS Independent
Requires-Python: >=3.11
License-File: LICENSE
Requires-Dist: intervaltree
Requires-Dist: matplotlib
Requires-Dist: networkx>=3.4.2
Requires-Dist: pandas
Requires-Dist: rich
Requires-Dist: seaborn
Requires-Dist: snakemake>=8.24
Requires-Dist: snakemake-executor-plugin-slurm
Requires-Dist: sqlalchemy>=2.0
Requires-Dist: typer>=0.12
Dynamic: license-file
